<?xml version = "1.0" encoding = "UTF-8"?>
<!DOCTYPE suite SYSTEM "http://testng.org/testng-1.0.dtd" >

<suite name="IOS" parallel="tests" thread-count="1">
    <test name="iPhone 8">
        <parameter name="wda" value="8200"/>
        <parameter name="node_port" value="4790"/>
        <parameter name="deviceName" value="iPhone 8"/>
        <parameter name="platformVersion" value="13.5"/>
        <classes>
            <class name="acceptanceTests.runners.IOSCucumberRunnerTest">
            </class>
        </classes>
    </test>

</suite>

